setup.py
strconv.py
strconv.egg-info/PKG-INFO
strconv.egg-info/SOURCES.txt
strconv.egg-info/dependency_links.txt
strconv.egg-info/pbr.json
strconv.egg-info/top_level.txt