Metadata-Version: 1.1
Name: strconv
Version: 0.4.1
Summary: String type inference and conversion
Home-page: https://github.com/bruth/strconv/
Author: Byron Ruth
Author-email: b@devel.io
License: BSD
Keywords: types inference conversion strings
Platform: UNKNOWN
Classifier: Development Status :: 3 - Alpha
Classifier: License :: OSI Approved :: BSD License
Classifier: Intended Audience :: Developers
Classifier: Programming Language :: Python :: 2.7
Classifier: Programming Language :: Python :: 3.2
Classifier: Programming Language :: Python :: 3.3
